CHANGES.txt
LICENSE.txt
MANIFEST.in
README.md
README_PYPI.md
RELEASE.md
setup.py
MedPy.egg-info/PKG-INFO
MedPy.egg-info/SOURCES.txt
MedPy.egg-info/dependency_links.txt
MedPy.egg-info/requires.txt
MedPy.egg-info/top_level.txt
bin/medpy_anisotropic_diffusion.py
bin/medpy_apparent_diffusion_coefficient.py
bin/medpy_binary_resampling.py
bin/medpy_convert.py
bin/medpy_create_empty_volume_by_example.py
bin/medpy_dicom_slices_to_volume.py
bin/medpy_dicom_to_4D.py
bin/medpy_diff.py
bin/medpy_extract_contour.py
bin/medpy_extract_min_max.py
bin/medpy_extract_sub_volume.py
bin/medpy_extract_sub_volume_auto.py
bin/medpy_extract_sub_volume_by_example.py
bin/medpy_fit_into_shape.py
bin/medpy_gradient.py
bin/medpy_graphcut_label.py
bin/medpy_graphcut_label_bgreduced.py
bin/medpy_graphcut_label_w_regional.py
bin/medpy_graphcut_label_wsplit.py
bin/medpy_graphcut_voxel.py
bin/medpy_grid.py
bin/medpy_info.py
bin/medpy_intensity_range_standardization.py
bin/medpy_intersection.py
bin/medpy_join_masks.py
bin/medpy_join_xd_to_xplus1d.py
bin/medpy_label_count.py
bin/medpy_label_fit_to_mask.py
bin/medpy_label_superimposition.py
bin/medpy_merge.py
bin/medpy_morphology.py
bin/medpy_resample.py
bin/medpy_reslice_3d_to_4d.py
bin/medpy_set_pixel_spacing.py
bin/medpy_shrink_image.py
bin/medpy_split_xd_to_xminus1d.py
bin/medpy_stack_sub_volumes.py
bin/medpy_swap_dimensions.py
bin/medpy_watershed.py
bin/medpy_zoom_image.py
lib/maxflow/src/README
lib/maxflow/src/block.h
lib/maxflow/src/graph.cpp
lib/maxflow/src/graph.h
lib/maxflow/src/instances.inc
lib/maxflow/src/maxflow.cpp
lib/maxflow/src/pythongraph.h
lib/maxflow/src/wrapper.cpp
medpy/__init__.py
medpy/core/__init__.py
medpy/core/exceptions.py
medpy/core/logger.py
medpy/features/__init__.py
medpy/features/histogram.py
medpy/features/intensity.py
medpy/features/texture.py
medpy/features/utilities.py
medpy/filter/IntensityRangeStandardization.py
medpy/filter/__init__.py
medpy/filter/binary.py
medpy/filter/houghtransform.py
medpy/filter/image.py
medpy/filter/label.py
medpy/filter/noise.py
medpy/filter/smoothing.py
medpy/filter/utilities.py
medpy/graphcut/__init__.py
