Metadata-Version: 2.1
Name: MedPy
Version: 0.5.2
Summary: Medical image processing in Python
Home-page: https://github.com/loli/medpy
Author: Oskar Maier
Author-email: oskar.maier@gmail.com
License: LICENSE.txt
Keywords: medical image processing dicom itk insight tool kit MRI CT US graph cut max-flow min-cut
Classifier: Development Status :: 5 - Production/Stable
Classifier: Environment :: Console
Classifier: Environment :: Other Environment
Classifier: Intended Audience :: End Users/Desktop
Classifier: Intended Audience :: Developers
Classifier: Intended Audience :: Healthcare Industry
Classifier: Intended Audience :: Science/Research
Classifier: License :: OSI Approved :: GNU General Public License (GPL)
Classifier: Operating System :: MacOS :: MacOS X
Classifier: Operating System :: Microsoft :: Windows
Classifier: Operating System :: POSIX
Classifier: Operating System :: Unix
Classifier: Programming Language :: Python :: 3 :: Only
Classifier: Programming Language :: Python :: 3.8
Classifier: Programming Language :: Python :: 3.9
Classifier: Programming Language :: Python :: 3.10
Classifier: Programming Language :: Python :: 3.11
Classifier: Programming Language :: C++
Classifier: Topic :: Scientific/Engineering :: Medical Science Apps.
Classifier: Topic :: Scientific/Engineering :: Image Recognition
Requires-Python: >=3.5, <4
License-File: LICENSE.txt
Requires-Dist: scipy>=1.10
Requires-Dist: numpy>=1.24
Requires-Dist: SimpleITK>=2.1
Provides-Extra: dev
Requires-Dist: pre-commit; extra == "dev"
Provides-Extra: test
Requires-Dist: pytest; extra == "test"
Requires-Dist: hypothesis; extra == "test"
Provides-Extra: watershed
Requires-Dist: scikit-image; extra == "watershed"
Provides-Extra: doc
Requires-Dist: sphinx>=1.6; extra == "doc"
Requires-Dist: numpydoc; extra == "doc"
Requires-Dist: pydata-sphinx-theme; extra == "doc"
